fynor/__init__.py
fynor/app.py
fynor/middleware.py
fynor/response.py
fynor-0.1.2.dist-info/licenses/LICENSE
fynor-0.1.2.dist-info/METADATA
fynor-0.1.2.dist-info/WHEEL
fynor-0.1.2.dist-info/top_level.txt
fynor-0.1.2.dist-info/RECORD
