Metadata-Version: 2.4
Name: fynor
Version: 0.1.2
Summary: Fynor is a lightweight WSGI web application framework.
Author-email: Abdelmajid Yunus <abdulmajidyunusov18@gmail.com>
License: MIT
Project-URL: Homepage, https://github.com/goldendevuz/fynor
Project-URL: Repository, https://github.com/goldendevuz/fynor
Project-URL: Issues, https://github.com/goldendevuz/fynor/issues
Keywords: wsgi,web,framework,jinja,parse,webob
Requires-Python: >=3.9
License-File: LICENSE
Requires-Dist: Jinja2<4.0,>=3.1
Requires-Dist: parse<2.0,>=1.20
Requires-Dist: WebOb<2.0,>=1.8
Requires-Dist: whitenoise<7.0,>=6.0
Provides-Extra: dev
Requires-Dist: twine>=4.0.0; extra == "dev"
Requires-Dist: wheel; extra == "dev"
Requires-Dist: build; extra == "dev"
Dynamic: license-file
